pyROTMOD/__init__.py
pyROTMOD/main.py
pyROTMOD/conf/__init__.py
pyROTMOD/conf/config_defaults.py
pyROTMOD/fitters/__init__.py
pyROTMOD/fitters/fitters.py
pyROTMOD/gas/__init__.py
pyROTMOD/gas/gas.py
pyROTMOD/optical/__init__.py
pyROTMOD/optical/calculate_profile_components.py
pyROTMOD/optical/conversions.py
pyROTMOD/optical/optical.py
pyROTMOD/optical/profile_functions.py
pyROTMOD/optical/profiles.py
pyROTMOD/rotmass/__init__.py
pyROTMOD/rotmass/potentials.py
pyROTMOD/rotmass/rotmass.py
pyROTMOD/rotmod/__init__.py
pyROTMOD/rotmod/rotmod.py
pyROTMOD/support/__init__.py
pyROTMOD/support/constants.py
pyROTMOD/support/errors.py
pyROTMOD/support/log_functions.py
pyROTMOD/support/major_functions.py
pyROTMOD/support/minor_functions.py
pyROTMOD/support/parameter_classes.py
pyROTMOD/support/profile_classes.py
pyROTMOD/support/vertical_profiles.py
pyrotmod-1.0.2.dist-info/METADATA
pyrotmod-1.0.2.dist-info/WHEEL
pyrotmod-1.0.2.dist-info/entry_points.txt
pyrotmod-1.0.2.dist-info/licenses/LICENSE
pyrotmod-1.0.2.dist-info/RECORD
